parmap/__init__.py
parmap/implentation.py
python_parmap-2.1.6.dist-info/LICENSE
python_parmap-2.1.6.dist-info/WHEEL
python_parmap-2.1.6.dist-info/METADATA
python_parmap-2.1.6.dist-info/RECORD
