Metadata-Version: 2.1
Name: python-parmap
Version: 2.1.6
Summary: Simple trivial parallelization
Home-page: https://github.com/fergalm/parmap
Author: Fergal
Author-email: fergal.mullally@gmail.com
Requires-Python: >3.7
Classifier: Programming Language :: Python :: 3
Classifier: Programming Language :: Python :: 3.10
Classifier: Programming Language :: Python :: 3.8
Classifier: Programming Language :: Python :: 3.9
